<?xml version="1.0" encoding="UTF-8"?>
<beans xmlns="http://www.springframework.org/schema/beans"
	xmlns:xsi="http://www.w3.org/2001/XMLSchema-instance"
	xsi:schemaLocation="
http://www.springframework.org/schema/beans
http://www.springframework.org/schema/beans/spring-beans-4.0.xsd
">
    <!--<bean id="fastDFSManager" class="com.jdd.fm.core.fdfs.FastDFSManager">
        <property  name="configPath" value="config/fdfs.conf" />
    </bean>-->

    <!-- 线程链接池 -->
    <!--<bean id="threadPoolTaskExecutor"-->
          <!--class="org.springframework.scheduling.concurrent.ThreadPoolTaskExecutor">-->
        <!--<property name="corePoolSize" value="10"/>-->
        <!--<property name="keepAliveSeconds" value="300"/>-->
        <!--<property name="maxPoolSize" value="200"/>-->
        <!--<property name="queueCapacity" value="200000"/>-->
    <!--</bean>-->
</beans>